confluent_kafka_wrapper/__init__.py
confluent_kafka_wrapper/consumer.py
confluent_kafka_wrapper/producer.py
confluent_kafka_wrapper-0.0.3.dist-info/LICENSE
confluent_kafka_wrapper-0.0.3.dist-info/METADATA
confluent_kafka_wrapper-0.0.3.dist-info/WHEEL
confluent_kafka_wrapper-0.0.3.dist-info/top_level.txt
confluent_kafka_wrapper-0.0.3.dist-info/RECORD
